README.md
setup.py
image_processing_by_cbcj/__init__.py
image_processing_by_cbcj.egg-info/PKG-INFO
image_processing_by_cbcj.egg-info/SOURCES.txt
image_processing_by_cbcj.egg-info/dependency_links.txt
image_processing_by_cbcj.egg-info/requires.txt
image_processing_by_cbcj.egg-info/top_level.txt
image_processing_by_cbcj/processing/__init__.py
image_processing_by_cbcj/processing/combination.py
image_processing_by_cbcj/processing/transformation.py
image_processing_by_cbcj/utils/__init__.py
image_processing_by_cbcj/utils/io.py
image_processing_by_cbcj/utils/plot.py