Metadata-Version: 2.1
Name: image-processing-by-cbcj
Version: 0.0.1
Summary: Image Precessing Package using skimage
Home-page: https://github.com/CleberJesus/image_processing_package
Author: Cleber Bianchi
